meta_weather_cli/__init__.py
meta_weather_cli/city.py
meta_weather_cli/cli.py
meta_weather_cli/country.py
meta_weather_cli-0.1.9.dist-info/entry_points.txt
meta_weather_cli-0.1.9.dist-info/WHEEL
meta_weather_cli-0.1.9.dist-info/METADATA
meta_weather_cli-0.1.9.dist-info/RECORD
