Metadata-Version: 2.1
Name: meta-weather-cli
Version: 0.1.9
Summary: A CLI to check weather in cities around the globe
Author: Omer Ben David
Requires-Python: >=3.9,<4.0
Classifier: Programming Language :: Python :: 3
Classifier: Programming Language :: Python :: 3.10
Classifier: Programming Language :: Python :: 3.9
